flota_app/__init__.py
flota_app/builders/__init__.py
flota_app/builders/basic_insurance_builder.py
flota_app/builders/basic_mot_builder.py
flota_app/builders/car_builder.py
flota_app/config/config_files/.env
flota_app/config/config_files/mail.env
flota_app/data/cars.json
flota_app/factory/__init__.py
flota_app/factory/converters/__init__.py
flota_app/factory/converters/converter.py
flota_app/factory/converters/to_car_converter.py
flota_app/factory/factories/__init__.py
flota_app/factory/factories/car_factories/__init__.py
flota_app/factory/factories/car_factories/csv_factories.py
flota_app/factory/factories/car_factories/json_factories.py
flota_app/factory/factories/car_factories/jsonl_factories.py
flota_app/factory/factories/car_factories/sqlite_factories.py
flota_app/factory/factories/car_factories/txt_factories.py
flota_app/factory/factories/car_factories/xlsx_factories.py
flota_app/factory/factories/data_factory.py
flota_app/factory/loaders/__init__.py
flota_app/factory/loaders/csv_loader.py
flota_app/factory/loaders/data_loader.py
flota_app/factory/loaders/json_loader.py
flota_app/factory/loaders/jsonl_loader.py
flota_app/factory/loaders/sqlite_loader.py
flota_app/factory/loaders/txt_loader.py
flota_app/factory/loaders/xlsx_loader.py
flota_app/factory/processors/__init__.py
flota_app/factory/processors/data_processor.py
flota_app/factory/validators/__init__.py
flota_app/factory/validators/json_dict_validator.py
flota_app/factory/validators/validator.py
flota_app/models/__init__.py
flota_app/models/car.py
flota_app/models/insurances/__init__.py
flota_app/models/insurances/basic_insurance.py
flota_app/models/insurances/dealership_insurance.py
flota_app/models/insurances/insurance.py
flota_app/models/mots/__init__.py
flota_app/models/mots/basic_mot.py
flota_app/models/mots/mot.py
flota_app/repo/__init__.py
flota_app/repo/cars_repo.py
flota_app/repo/insurances_repo.py
flota_app/repo/mots_repo.py
flota_app/services/__init__.py
flota_app-0.1.3.dist-info/METADATA
flota_app-0.1.3.dist-info/WHEEL
flota_app-0.1.3.dist-info/RECORD
